{"Cut":{"Clocks":[{"Apple":217,"Apricot":110,"Banana":110},{"Apple":213,"Apricot":108,"Banana":111},{"Apple":215,"Apricot":111,"Banana":110}]},"Points":[{"Dump":null,"Id":"","VectorClock":"Fv+BBAEBBlZDbG9jawH/ggABDAEGAAAd/4IAAwVBcHBsZf/ZBkJhbmFuYW4HQXByaWNvdG4=","CommunicationDelta":0},{"Dump":[{"VarName":"Banana-r.Term","Value":2,"Type":"int"},{"VarName":"Banana-r.Vote","Value":-9223372036854775808,"Type":"int"},{"VarName":"Banana-r.checkQuorum","Value":true,"Type":"boolean"},{"VarName":"Banana-r.electionElapsed","Value":0,"Type":"int"},{"VarName":"Banana-r.electionTimeout","Value":10,"Type":"int"},{"VarName":"Banana-r.heartbeatElapsed","Value":0,"Type":"int"},{"VarName":"Banana-r.heartbeatTimeout","Value":1,"Type":"int"},{"VarName":"Banana-r.id","Value":-9223372036854775808,"Type":"int"},{"VarName":"Banana-r.lead","Value":-9223372036854775808,"Type":"int"},{"VarName":"Banana-r.leadTransferee","Value":0,"Type":"int"},{"VarName":"Banana-r.pendingConf","Value":false,"Type":"boolean"},{"VarName":"Banana-r.raftLog.applied","Value":38,"Type":"int"},{"VarName":"Banana-r.raftLog.committed","Value":38,"Type":"int"},{"VarName":"Banana-r.raftLog.lastIndex","Value":39,"Type":"int"},{"VarName":"Banana-r.raftLog.lastTerm","Value":2,"Type":"int"},{"VarName":"Banana-r.randomizedElectionTimeout","Value":13,"Type":"int"},{"VarName":"Banana-r.readState","Value":{"Index":0,"RequestCtx":null},"Type":""},{"VarName":"Banana-r.state","Value":"\u0000","Type":"string"}],"Id":"53a0acfad59379b3e050338bf9f23cfc172ee787","VectorClock":"Fv+BBAEBBlZDbG9jawH/ggABDAEGAAAd/4IAAwVBcHBsZf/VBkJhbmFuYW8HQXByaWNvdGw=","CommunicationDelta":0},{"Dump":null,"Id":"","VectorClock":"Fv+BBAEBBlZDbG9jawH/ggABDAEGAAAd/4IAAwVBcHBsZf/XBkJhbmFuYW4HQXByaWNvdG8=","CommunicationDelta":0}],"TotalOrdering":[[0],[1],[2]]}
{"Cut":{"Clocks":[{"Apple":520,"Apricot":267,"Banana":265},{"Apple":512,"Apricot":262,"Banana":266},{"Apple":517,"Apricot":267,"Banana":265}]},"Points":[{"Dump":null,"Id":"","VectorClock":"Fv+BBAEBBlZDbG9jawH/ggABDAEGAAAi/4IAAwZCYW5hbmH+AQkHQXByaWNvdP4BCwVBcHBsZf4CCA==","CommunicationDelta":0},{"Dump":null,"Id":"","VectorClock":"Fv+BBAEBBlZDbG9jawH/ggABDAEGAAAi/4IAAwdBcHJpY290/gEGBUFwcGxl/gIABkJhbmFuYf4BCg==","CommunicationDelta":0},{"Dump":[{"VarName":"Apricot-r.Term","Value":2,"Type":"int"},{"VarName":"Apricot-r.Vote","Value":-9223372036854775808,"Type":"int"},{"VarName":"Apricot-r.checkQuorum","Value":true,"Type":"boolean"},{"VarName":"Apricot-r.electionElapsed","Value":0,"Type":"int"},{"VarName":"Apricot-r.electionTimeout","Value":10,"Type":"int"},{"VarName":"Apricot-r.heartbeatElapsed","Value":0,"Type":"int"},{"VarName":"Apricot-r.heartbeatTimeout","Value":1,"Type":"int"},{"VarName":"Apricot-r.id","Value":-9223372036854775808,"Type":"int"},{"VarName":"Apricot-r.lead","Value":-9223372036854775808,"Type":"int"},{"VarName":"Apricot-r.leadTransferee","Value":0,"Type":"int"},{"VarName":"Apricot-r.pendingConf","Value":false,"Type":"boolean"},{"VarName":"Apricot-r.raftLog.applied","Value":84,"Type":"int"},{"VarName":"Apricot-r.raftLog.committed","Value":84,"Type":"int"},{"VarName":"Apricot-r.raftLog.lastIndex","Value":85,"Type":"int"},{"VarName":"Apricot-r.raftLog.lastTerm","Value":2,"Type":"int"},{"VarName":"Apricot-r.randomizedElectionTimeout","Value":18,"Type":"int"},{"VarName":"Apricot-r.readState","Value":{"Index":0,"RequestCtx":null},"Type":""},{"VarName":"Apricot-r.state","Value":"\u0000","Type":"string"}],"Id":"53a0acfad59379b3e050338bf9f23cfc172ee787","VectorClock":"Fv+BBAEBBlZDbG9jawH/ggABDAEGAAAi/4IAAwVBcHBsZf4CBQZCYW5hbmH+AQkHQXByaWNvdP4BCw==","CommunicationDelta":0}],"TotalOrdering":[[0,2],[1]]}
{"Cut":{"Clocks":[{"Apple":751,"Apricot":381,"Banana":386},{"Apple":748,"Apricot":381,"Banana":386},{"Apple":749,"Apricot":382,"Banana":383}]},"Points":[{"Dump":null,"Id":"","VectorClock":"Fv+BBAEBBlZDbG9jawH/ggABDAEGAAAi/4IAAwVBcHBsZf4C7wZCYW5hbmH+AYIHQXByaWNvdP4BfQ==","CommunicationDelta":0},{"Dump":[{"VarName":"Banana-r.Term","Value":2,"Type":"int"},{"VarName":"Banana-r.Vote","Value":-9223372036854775808,"Type":"int"},{"VarName":"Banana-r.checkQuorum","Value":true,"Type":"boolean"},{"VarName":"Banana-r.electionElapsed","Value":0,"Type":"int"},{"VarName":"Banana-r.electionTimeout","Value":10,"Type":"int"},{"VarName":"Banana-r.heartbeatElapsed","Value":0,"Type":"int"},{"VarName":"Banana-r.heartbeatTimeout","Value":1,"Type":"int"},{"VarName":"Banana-r.id","Value":-9223372036854775808,"Type":"int"},{"VarName":"Banana-r.lead","Value":-9223372036854775808,"Type":"int"},{"VarName":"Banana-r.leadTransferee","Value":0,"Type":"int"},{"VarName":"Banana-r.pendingConf","Value":false,"Type":"boolean"},{"VarName":"Banana-r.raftLog.applied","Value":117,"Type":"int"},{"VarName":"Banana-r.raftLog.committed","Value":118,"Type":"int"},{"VarName":"Banana-r.raftLog.lastIndex","Value":118,"Type":"int"},{"VarName":"Banana-r.raftLog.lastTerm","Value":2,"Type":"int"},{"VarName":"Banana-r.randomizedElectionTimeout","Value":13,"Type":"int"},{"VarName":"Banana-r.readState","Value":{"Index":0,"RequestCtx":null},"Type":""},{"VarName":"Banana-r.state","Value":"\u0000","Type":"string"}],"Id":"53a0acfad59379b3e050338bf9f23cfc172ee787","VectorClock":"Fv+BBAEBBlZDbG9jawH/ggABDAEGAAAi/4IAAwVBcHBsZf4C7AZCYW5hbmH+AYIHQXByaWNvdP4BfQ==","CommunicationDelta":0},{"Dump":null,"Id":"","VectorClock":"Fv+BBAEBBlZDbG9jawH/ggABDAEGAAAi/4IAAwVBcHBsZf4C7QZCYW5hbmH+AX8HQXByaWNvdP4Bfg==","CommunicationDelta":0}],"TotalOrdering":[[0,1],[2]]}
